blockunblockips/README.MD
blockunblockips/__init__.py
blockunblockips/requirements.txt
blockunblockips/thirdparty.json
blockunblockips-0.10.dist-info/LICENSE.rst
blockunblockips-0.10.dist-info/METADATA
blockunblockips-0.10.dist-info/WHEEL
blockunblockips-0.10.dist-info/top_level.txt
blockunblockips-0.10.dist-info/RECORD
