Metadata-Version: 2.1
Name: blockunblockips
Version: 0.10
Summary: Block / unblock ips using the Windows Firewall
Home-page: https://github.com/hansalemaos/blockunblockips
Author: Johannes Fischer
Author-email: aulasparticularesdealemaosp@gmail.com
License: MIT
Keywords: block,unblock,ips,firewall
Classifier: Development Status :: 4 - Beta
Classifier: Programming Language :: Python :: 3 :: Only
Classifier: Programming Language :: Python :: 3.10
Classifier: Topic :: Software Development :: Libraries :: Python Modules
Classifier: Topic :: Utilities
License-File: LICENSE.rst
Requires-Dist: detachedproc
